MANIFEST.in
README.md
VERSION
setup.py
WTF_OTP.egg-info/PKG-INFO
WTF_OTP.egg-info/SOURCES.txt
WTF_OTP.egg-info/dependency_links.txt
WTF_OTP.egg-info/not-zip-safe
WTF_OTP.egg-info/requires.txt
WTF_OTP.egg-info/top_level.txt
tests/fields/__init__.py
tests/fields/test_secret_fields.py
tests/validators/__init__.py
tests/validators/test_common.py
tests/validators/test_hotp_check.py
tests/validators/test_totp_check.py
tests/widgets/__init__.py
tests/widgets/test_secret_widget.py
wtf_otp/__init__.py
wtf_otp/fields/__init__.py
wtf_otp/fields/secret_key.py
wtf_otp/validators/__init__.py
wtf_otp/validators/otp.py
wtf_otp/widgets/__init__.py
wtf_otp/widgets/secret_key_widget.py
wtf_otp/widgets/templates/angular_script.js
wtf_otp/widgets/templates/jquery_script.js
wtf_otp/widgets/templates/tags.html
wtf_otp/widgets/templates/widget.html