Metadata-Version: 2.1
Name: WTF-OTP
Version: 0.7.10
Summary: One-Time Password for WTForms
Home-page: https://github.com/hiroaki-yamamoto/WTF-OTP
Author: Hiroaki Yamamoto
Author-email: hiroaki@hysoftware.net
License: MIT
Keywords: WTForms WT-Forms OTP One Time Password
Classifier: License :: OSI Approved :: MIT License
Classifier: Intended Audience :: Developers
Classifier: Topic :: Internet :: WWW/HTTP :: Dynamic Content :: CGI Tools/Libraries
Classifier: Topic :: Internet :: WWW/HTTP :: WSGI :: Middleware
Classifier: Topic :: Software Development :: Libraries :: Python Modules
Classifier: Framework :: Flask
